LICENSE
MANIFEST.in
README.md
requirements.txt
setup.py
segsoup/__init__.py
segsoup.egg-info/PKG-INFO
segsoup.egg-info/SOURCES.txt
segsoup.egg-info/dependency_links.txt
segsoup.egg-info/requires.txt
segsoup.egg-info/top_level.txt
segsoup/soup/__init__.py
segsoup/soup/soup.py
segsoup/strategies/__init__.py
segsoup/strategies/greedy.py
segsoup/strategies/uniform.py
segsoup/strategies/weighted.py
segsoup/utils/__init__.py
segsoup/utils/utils.py