Metadata-Version: 2.4
Name: segsoup
Version: 0.1.1
Summary: Library for the construction of instance segmentation model soups.
Home-page: https://github.com/joortif/SegSoup
Author: Joaquin Ortiz de Murua Ferrero
Author-email: joortif@unirioja.es
Maintainer: Joaquin Ortiz de Murua Ferrero
Maintainer-email: joortif@unirioja.es
License: MIT license
Keywords: instance semantic segmentation image deep learning computer vision model soup
Classifier: Development Status :: 4 - Beta
Classifier: Programming Language :: Python :: 3.10
Classifier: Intended Audience :: Science/Research
Classifier: Intended Audience :: Developers
Classifier: Topic :: Scientific/Engineering :: Image Recognition
Classifier: Topic :: Scientific/Engineering :: Artificial Intelligence
Classifier: Operating System :: OS Independent
Requires-Python: >=3.9
License-File: LICENSE
Requires-Dist: setuptools>=80.9.0
Requires-Dist: torch>=2.8.0
Dynamic: author
Dynamic: author-email
Dynamic: classifier
Dynamic: description
Dynamic: description-content-type
Dynamic: home-page
Dynamic: keywords
Dynamic: license
Dynamic: license-file
Dynamic: maintainer
Dynamic: maintainer-email
Dynamic: requires-dist
Dynamic: requires-python
Dynamic: summary
